roboka/__init__.py
roboka/client.py
roboka-0.3.6.dist-info/licenses/LICENSE
roboka-0.3.6.dist-info/METADATA
roboka-0.3.6.dist-info/WHEEL
roboka-0.3.6.dist-info/top_level.txt
roboka-0.3.6.dist-info/RECORD
