Metadata-Version: 2.4
Name: roboka
Version: 0.3.6
Summary: A Python wrapper for Rubika bot API. can you read documents in rb-chat.ir site or this github page: https://github.com/aliz17-web/roboka
Author-email: Ali Zolghadr <tradecoinex5@gmail.com>
License: Proprietary
Project-URL: Homepage, https://rb-chat.ir
Project-URL: Documentation, https://rb-chat.ir
Requires-Python: >=3.8
License-File: LICENSE
Requires-Dist: requests
Dynamic: license-file
